alignmentrs/__init__.py
alignmentrs/util.py
alignmentrs/aln/__init__.py
alignmentrs/aln/classes.py
alignmentrs/aln/funcs.py
alignmentrs/alnset/__init__.py
alignmentrs/alnset/classes.py
alignmentrs/alnset/funcs.py
alignmentrs/extras/__init__.py
alignmentrs/extras/numpy.py
alignmentrs/extras/pandas.py
libalignmentrs/alignment.cpython-35m-darwin.so
libalignmentrs/alignment.cpython-36m-darwin.so
libalignmentrs/position.cpython-35m-darwin.so
libalignmentrs/position.cpython-36m-darwin.so
libalignmentrs/record.cpython-35m-darwin.so
libalignmentrs/record.cpython-36m-darwin.so
alignmentrs-0.9.0.dist-info/LICENSE
alignmentrs-0.9.0.dist-info/METADATA
alignmentrs-0.9.0.dist-info/WHEEL
alignmentrs-0.9.0.dist-info/top_level.txt
alignmentrs-0.9.0.dist-info/RECORD
